stridesduplicatefinder/README.MD
stridesduplicatefinder/__init__.py
stridesduplicatefinder/requirements.txt
stridesduplicatefinder/thirdparty.json
stridesduplicatefinder-0.10.dist-info/LICENSE.rst
stridesduplicatefinder-0.10.dist-info/METADATA
stridesduplicatefinder-0.10.dist-info/WHEEL
stridesduplicatefinder-0.10.dist-info/top_level.txt
stridesduplicatefinder-0.10.dist-info/RECORD
