Metadata-Version: 2.1
Name: stridesduplicatefinder
Version: 0.10
Summary: Calculate overlapping values between two arrays and return the results as a DataFrame
Home-page: https://github.com/hansalemaos/stridesduplicatefinder
Author: Johannes Fischer
Author-email: aulasparticularesdealemaosp@gmail.com
License: MIT
Keywords: numpy,numexpr,strides
Classifier: Development Status :: 4 - Beta
Classifier: Programming Language :: Python :: 3 :: Only
Classifier: Programming Language :: Python :: 3.10
Classifier: Topic :: Software Development :: Libraries :: Python Modules
Classifier: Topic :: Utilities
License-File: LICENSE.rst
Requires-Dist: numexpr
Requires-Dist: numpy
Requires-Dist: pandas
